LICENSE.txt
MANIFEST.in
README.rst
requirements-dev.txt
requirements.txt
setup.py
tox.ini
aboutyou/__init__.py
aboutyou/api.py
aboutyou/auth.py
aboutyou/config.py
aboutyou/constants.py
aboutyou/shop.py
aboutyou.egg-info/PKG-INFO
aboutyou.egg-info/SOURCES.txt
aboutyou.egg-info/dependency_links.txt
aboutyou.egg-info/requires.txt
aboutyou.egg-info/top_level.txt
aboutyou/django/__init__.py
aboutyou/django/backend.py
aboutyou/django/middleware.py
doc/Makefile
doc/aboutyou_objects.rst
doc/api.rst
doc/auth.rst
doc/collins_objects.gv
doc/conf.py
doc/config.rst
doc/constants.rst
doc/difference.rst
doc/index.rst
doc/make.bat
doc/shop.rst
doc/django/backend.rst
doc/django/middleware.rst
doc/howtos/caching.rst
doc/howtos/django.rst
doc/howtos/howtos.rst
doc/howtos/usage.rst
examples/basket.py
examples/category_tree.py
examples/config.json
examples/config.yaml
examples/credentials.yml
examples/extending_config.py
examples/get_brand.py
examples/django/token.js
test/conftest.py
test/test_api.py
test/test_auth.py
test/test_config.py
test/test_shop.py