Metadata-Version: 1.1
Name: aboutyou
Version: 1.0
Summary: A connection to the aboutyou.de shop.
Home-page: https://bitbucket.org/slicedice/aboutyou-shop-sdk-python/overview
Author: Arne Simon
Author-email: arne.simon@slice-dice.de
License: MIT
Download-URL: https://bitbucket.org/slicedice/aboutyou-shop-sdk-python/downloads
Keywords: aboutyou,shop,collins,api
Platform: UNKNOWN
Classifier: Programming Language :: Python :: 2.7
Classifier: Programming Language :: Python :: 3.4
Classifier: Topic :: Internet
Classifier: Topic :: Office/Business
